pp.py
pp_bz-1.2.2.dist-info/DESCRIPTION.rst
pp_bz-1.2.2.dist-info/METADATA
pp_bz-1.2.2.dist-info/RECORD
pp_bz-1.2.2.dist-info/WHEEL
pp_bz-1.2.2.dist-info/entry_points.txt
pp_bz-1.2.2.dist-info/metadata.json
pp_bz-1.2.2.dist-info/top_level.txt
